Metadata-Version: 2.1
Name: zombie-dice
Version: 0.3
Summary: Zombie Dice
Home-page: https://github.com/feeblefruits/zombiedice
Author: Jacques Coetzee
Author-email: j.coetzee0@gmail.com
License: UNKNOWN
Platform: UNKNOWN
Classifier: Programming Language :: Python :: 3
Classifier: License :: OSI Approved :: MIT License
Classifier: Operating System :: OS Independent
Requires-Python: >=3.6
